{
"content": {
"body": {
"preview": "smth to test  https://i.gifer.com/1HOf.gif youtube doesn't know such video Jean-Frédéric Phélypeaux, Count of Maurepas # #painter  @tst1vpxtrkjc\n{{Infobox officeholder\n| name             = The Count…"
},
"tags": [
"test"
],
"title": "Hermes fights with Daedalus against Phoebe",
"embeds": [
{
"_id": "Mock",
"id": "Mock",
"type": "oembed",
"result": {
"type": "video",
"version": "1.0",
"title": "Mr. Trololo original upload",
"url": "https://www.youtube.com/watch?v=oavMtUWDBTM",
"author": "RealPapaPit",
"author_url": "https://www.youtube.com/user/RealPapaPit",
"provider_name": "YouTube",
"description": "Я очень рад, ведь я, наконец, возвращаюсь домой. Оригинальный клип. Исполняет Эдуард Хиль.",
"thumbnail_url": "https://i.ytimg.com/vi/oavMtUWDBTM/hqdefault.jpg",
"thumbnail_width": 480,
"thumbnail_height": 360,
"html": "<div><div style=\"left: 0; width: 100%; height: 0; position: relative; padding-bottom: 74.9457%;\"><iframe src=\"https://www.youtube.com/embed/oavMtUWDBTM?feature=oembed\" style=\"border: 0; top: 0; left: 0; width: 100%; height: 100%; position: absolute;\" allowfullscreen scrolling=\"no\"></iframe></div></div>"
}
}
]
},
"votes": {
"upCount": 1,
"downCount": 0,
"hasUpVote": false,
"hasDownVote": false
},
"stats": {
"commentsCount": 1
},
"payout": {
"rShares": 499362573733504
},
"contentId": {
"userId": "tst2vkqehnse",
"permlink": "___mock___",
"refBlockNum": 3136
},
"meta": {
"time": "2019-04-19T12:58:09.000Z"
},
"author": {
"userId": "tst2vkqehnse",
"username": "tst2vkqehnse"
},
"community": {
"id": "gls",
"name": "GOLOS",
"avatarUrl": "none"
}
}
